kylerpdf/__init__.py
kylerpdf/pdf2image.py
kylerpdf/pdf2text.py
kylerpdf-1.0.dist-info/METADATA
kylerpdf-1.0.dist-info/WHEEL
kylerpdf-1.0.dist-info/top_level.txt
kylerpdf-1.0.dist-info/RECORD
